zikomo/__init__.py
zikomo/__main__.bk.py
zikomo/__main__.py
zikomo/constants.py
zikomo/database_helper.py
zikomo/discord_bot.py
zikomo/email_template.html
zikomo/git_utils.py
zikomo/helper.py
zikomo/migrate_db.py
zikomo/package_info.md
zikomo/utils.py
zikomo/whatsapp_utils.py
zikomo-1.2.4.dist-info/METADATA
zikomo-1.2.4.dist-info/WHEEL
zikomo-1.2.4.dist-info/entry_points.txt
zikomo-1.2.4.dist-info/top_level.txt
zikomo-1.2.4.dist-info/RECORD
