Metadata-Version: 2.4
Name: zikomo
Version: 1.2.4
Summary: Zikomo Deployment CLI
Author: Imran A. Shah
Author-email: imran.shah@zikomosolutions.com
License: Private License
Classifier: License :: Other/Proprietary License
Requires-Python: >=3.11
Dynamic: author
Dynamic: author-email
Dynamic: classifier
Dynamic: description
Dynamic: description-content-type
Dynamic: license
Dynamic: requires-python
Dynamic: summary
